qoi-0.7.2.dist-info/LICENSE
qoi-0.7.2.dist-info/WHEEL
qoi-0.7.2.dist-info/RECORD
qoi-0.7.2.dist-info/top_level.txt
qoi-0.7.2.dist-info/METADATA
qoi/benchmark.py
qoi/qoi.cpython-310-x86_64-linux-gnu.so
qoi/qoi.pxd
qoi/_version.py
qoi/__init__.py
