Metadata-Version: 2.2
Name: qoi
Version: 0.7.2
Summary: A simpler wrapper around qoi (https://github.com/phoboslab/qoi)
Home-page: https://github.com/kodonnell/qoi
Author: kodonnell
Author-email: kodonnell@users.noreply.github.com
License: MIT
Project-URL: Bug Tracker, https://github.com/kodonnell/qoi/issues
Keywords: qoi
Classifier: Programming Language :: Python :: 3
Classifier: License :: OSI Approved :: MIT License
Classifier: Operating System :: OS Independent
Classifier: Topic :: Scientific/Engineering :: Image Processing
Requires-Python: >=3.8
License-File: LICENSE
Requires-Dist: numpy>=1.22.4
Provides-Extra: dev
Requires-Dist: Cython>=3.0.0; extra == "dev"
Requires-Dist: pytest; extra == "dev"
Requires-Dist: pillow; extra == "dev"
Requires-Dist: opencv-python-headless; extra == "dev"
Requires-Dist: build; extra == "dev"
Requires-Dist: twine; extra == "dev"
Dynamic: provides-extra
Dynamic: requires-dist
